pyluxcore.oidn/oidnDenoise
pyluxcore-2.10.0.dist-info/RECORD
pyluxcore-2.10.0.dist-info/WHEEL
pyluxcore-2.10.0.dist-info/entry_points.txt
pyluxcore-2.10.0.dist-info/METADATA
pyluxcore-2.10.0.dist-info/licenses/COPYING.txt
pyluxcore-2.10.0.dist-info/licenses/AUTHORS.txt
pyluxcore/__init__.py
pyluxcore/pyluxcore.cpython-310-darwin.so
pyluxcore/.dylibs/libtbbmalloc.2.12.dylib
pyluxcore/.dylibs/libtbbmalloc_proxy.2.12.dylib
pyluxcore/.dylibs/libembree3.3.13.5.dylib
pyluxcore/.dylibs/libOpenImageDenoise_device_cpu.2.3.1.dylib
pyluxcore/.dylibs/libOpenImageDenoise_core.2.3.1.dylib
pyluxcore/.dylibs/libOpenImageDenoise.2.3.1.dylib
pyluxcore/.dylibs/libtbb.12.12.dylib
pyluxcoretest/__init__.py
pyluxcoretest/pyluxcoretest.py
pyluxcoretest/memorial.pfm
pyluxcoretest/__main__.py
pyluxcoretest/scenes/simple-mat/arch.exr
pyluxcoretest/scenes/luxball/luxball-shadowcatcher.scn
pyluxcoretest/scenes/luxball/luxball-shadowcatcher2.scn
pyluxcoretest/scenes/luxball/roadenv.jpg
pyluxcoretest/scenes/luxball/luxball-hdr-mix.scn
pyluxcoretest/scenes/luxball/luxball-hdr-ortho.scn
pyluxcoretest/scenes/luxball/Cr.nk
pyluxcoretest/scenes/luxball/luxball-velvet.cfg
pyluxcoretest/scenes/luxball/proctexball-mix.scn
pyluxcoretest/scenes/luxball/luxball-hdr-motionmesh.scn
pyluxcoretest/scenes/luxball/luxball-glossy2.scn
pyluxcoretest/scenes/luxball/luxball-hdr.scn
pyluxcoretest/scenes/luxball/luxball-backimg.scn
pyluxcoretest/scenes/luxball/luxball-glossycoat.cfg
pyluxcoretest/scenes/luxball/luxball-copper.cfg
pyluxcoretest/scenes/luxball/luxball-hdr-ortho.cfg
pyluxcoretest/scenes/luxball/luxball-hdr-mix.cfg
pyluxcoretest/scenes/luxball/luxball-shadowcatcher2.cfg
pyluxcoretest/scenes/luxball/luxball-shadowcatcher.cfg
pyluxcoretest/scenes/luxball/room.ply
pyluxcoretest/scenes/luxball/luxball-velvet.scn
pyluxcoretest/scenes/luxball/luxball-copper.scn
pyluxcoretest/scenes/luxball/luxball-glossycoat.scn
pyluxcoretest/scenes/luxball/luxball-backimg.cfg
pyluxcoretest/scenes/luxball/domingo_145.cube
pyluxcoretest/scenes/luxball/luxball-hdr.cfg
pyluxcoretest/scenes/luxball/luxball-glossy2.cfg
pyluxcoretest/scenes/luxball/proctexball-mix.cfg
pyluxcoretest/scenes/luxball/luxball-hdr-motionmesh.cfg
