Metadata-Version: 2.2
Name: pyluxcore
Version: 2.10.0
Summary: LuxCore Python bindings
Keywords: raytracing,ray tracing,rendering,pbr,physical based rendering,path tracing
Author: LuxCoreRender
Classifier: License :: OSI Approved :: Apache Software License
Classifier: Intended Audience :: Developers
Classifier: Programming Language :: Python :: 3.9
Classifier: Programming Language :: Python :: 3.10
Classifier: Programming Language :: Python :: 3.11
Classifier: Programming Language :: Python :: 3.12
Classifier: Programming Language :: Python :: 3.13
Classifier: Development Status :: 7 - Inactive
Classifier: Topic :: Multimedia :: Graphics :: 3D Rendering
Project-URL: Homepage, https://luxcorerender.org/
Project-URL: Documentation, http://wiki.luxcorerender.org/LuxCoreRender_Wiki
Project-URL: GitHub, https://github.com/LuxCoreRender/LuxCore
Requires-Python: >=3.8
Requires-Dist: numpy>=2; python_version > "3.8"
Requires-Dist: numpy<2; python_version <= "3.8"
Requires-Dist: nvidia-cuda-nvrtc-cu12; sys_platform != "darwin"
